[
  {
    "part_number": "867Z2251-28"
  },
  {
    "part_number": "867Z2251-29"
  },
  {
    "part_number": "867Z2251-32"
  },
  {
    "part_number": "867Z2251-94"
  },
  {
    "part_number": "867Z2251-95"
  },
  {
    "part_number": "867Z2251-98"
  },
  {
    "part_number": "LA-GR-100"
  },
  {
    "part_number": "LA-GR-101"
  },
  {
    "part_number": "LA-GR-099"
  },
  {
    "part_number": "LA-GR-108"
  },
  {
    "part_number": "LA-GR-178"
  },
  {
    "part_number": "TF104544"
  },
  {
    "part_number": "TF104545"
  },
  {
    "part_number": "TF104543"
  },
  {
    "part_number": "TF104550"
  },
  {
    "part_number": "TF104574"
  },
  {
    "part_number": "A511351610-057"
  },
  {
    "part_number": "A511351610-058"
  },
  {
    "part_number": "A511351610-059"
  },
  {
    "part_number": "A511351610-060"
  },
  {
    "part_number": "A511351610-061"
  },
  {
    "part_number": "A511351610-001"
  },
  {
    "part_number": "A511351610-002"
  },
  {
    "part_number": "A511351610-003"
  },
  {
    "part_number": "A511351610-004"
  },
  {
    "part_number": "A511351610-005"
  },
  {
    "part_number": "A511351610-006"
  },
  {
    "part_number": "A511351610-011"
  },
  {
    "part_number": "A511351610-012"
  },
  {
    "part_number": "A511351610-013"
  },
  {
    "part_number": "A511351610-014"
  },
  {
    "part_number": "A511351610-015"
  },
  {
    "part_number": "A511351610-017"
  },
  {
    "part_number": "A511351610-018"
  },
  {
    "part_number": "A511351610-019"
  },
  {
    "part_number": "A511351610-020"
  },
  {
    "part_number": "A511351610-021"
  },
  {
    "part_number": "A511351610-022"
  },
  {
    "part_number": "A511351610-023"
  },
  {
    "part_number": "A511351610-024"
  },
  {
    "part_number": "A511351610-025"
  }
]
